easyquiz/__init__.py
easyquiz/easyquiz.py
easyquiz/langs.json
easyquiz-0.2.dist-info/LICENSE
easyquiz-0.2.dist-info/METADATA
easyquiz-0.2.dist-info/WHEEL
easyquiz-0.2.dist-info/top_level.txt
easyquiz-0.2.dist-info/RECORD
