Metadata-Version: 2.1
Name: easyquiz
Version: 0.2
Summary: Module to create quick quizzes for IPython
Home-page: https://github.com/plapenamanero/easyquiz
Author: Pablo Lapeña Mañero
Author-email: plapenamanero@gmail.com
License: UNKNOWN
Download-URL: https://github.com/plapenamanero/easyquiz/archive/refs/tags/v0.2.tar.gz
Platform: UNKNOWN
Classifier: Development Status :: 4 - Beta
Classifier: Framework :: IPython
Classifier: Framework :: Jupyter
Classifier: Intended Audience :: Education
Classifier: License :: OSI Approved :: MIT License
Classifier: Natural Language :: English
Classifier: Operating System :: OS Independent
Classifier: Programming Language :: Python :: 3
License-File: LICENSE
Requires-Dist: ipywidgets (>=7.6.5)
